[
  {
    "chapter": "",
    "questions": [
      "عرف النحو مع بيان غرضه وموضوعه",
      "اذكر فائدة علم النحو",
      "عرف الكلمة وعدد أقسامها"
    ]
  },
  {
    "chapter": "أسثلة الكلمة (اسم وفعل وحرف)",
    "questions": [
      "عرف الاسم وبين فوائد قيود تعريفه، ثم أوضحه بمثال",
      "عدد علامات الاسم مع ذكر مثال لكل واحدة منها",
      "اذكر تعريف الفعل، ومثل لذلك",
      "عدد علامات الفعل ومثل لكل واحدة منها",
      "اذكر تعريف الحرف ومثل له",
      "بين فوائد الحرف ومثل لها"
    ]
  },
  {
    "chapter": "أسثلة الجملة",
    "questions": [
      "عرف الكلام والإسناد ووضحهما بمثال",
      "متى تكون اللفظ كلاما؟ وضح ذلك بأمثلة",
      "اذكر أقسام الجملة، ومثل لها",
      "أوضح الاعتراض والجواب في انحصار الكلام في القسمين المذكورين"
    ]
  },
  {
    "chapter": "أسثلة المعرب",
    "questions": [
      "عرف الاسم المعرب ومثل له",
      "ما هو الاسم المتمكن؟ اضرب مثالا له",
      "ما معنى الإعراب؟",
      "اذكر أنواع إعراب الاسم ثم عين العلامات لكل منها",
      "عرف العامل وبين محل الإعراب",
      "ما هو الاسم الجاري مجرى الصحيح؟ ومثل له",
      "كيف يعرب كل من الاسم المفرد المنصرف الصحيح، والجاري مجرى الصحيح والجمع المكسر المنصرف؟",
      "اذكر كيفية إعراب جمع المؤنث السالم، ومثل لذلك",
      "بم يعرب الاسم الغير المنصرف؟ هات مثالا يوضح ذلك",
      "اذكر الأسماء الستة وبين علامات إعرابها مع ذكر أمثلة",
      "كم شرطا لذلك الإعراب وماهي؟ ثم بين إعرابها عند فوات كل شرط منها",
      "ما هو إعراب المثنى؟ بين بالتمثيل",
      "ما هو إعراب كلا وكلتا إذا أضيفتا إلى الضمير؟ وما هو إعرابهما إذا أضيفتا إلى المظهر؟ مثل لكل منهم",
      "ما هو إعراب جمع المذكر السالم وما هي ملحقاته؟ أوضح بالأمثلة. ثم اذكر من القرآن الكريم شواهد 'أولو' رفعا ونصبا وجرا",
      "ما هي حركة نوني التثنية والجمع دائما؟ مثل لهما",
      "متى تسقط نونا التثنية وجمع المذكر السالم؟ أجب بأمثلة مفيدة",
      "أي الأسماء تقدر فيه جميع علامات إعرابها؟ اذكرها مع مثال",
      "عرف الاسم المنقوص وبين علامات إعرابه مع ضرب أمثلة",
      "كيف يكون إعراب جمع المذكر السالم إذا أضيف إلى ياء المتكلم؟ مثل لذلك"
    ]
  },
  {
    "chapter": "أسثلة المنصرف وغير المنصرف",
    "questions": [
      "كم قسما للاسم المعرب وما هي؟",
      "عرف المنصرف وبين حكمه مع مثال",
      "عرف غير المنصرف وبين حكمه",
      "كم سببا لمنع الصرف وما هي؟ عدده",
      "عرف العدل وبين أقسامه مع ذكر أمثلة",
      "ما السببان اللذان يجتمع معهما العدل؟ أوضح بمثالين",
      "ما هو الوصف لغة واصطلاحا؟ وما هو شرطه؟ أوضح بأمثلة",
      "اذكر شرط التأنيث بالتاء ومثل له",
      "اكتب شرط جواز تأثير المؤنث المعنوي وشرط وجوب تأثيره، ومثل لكل صورة",
      "ماذا حكم المؤنث المعنوي إذا كان علما ثلاثيا ساكن الأوسط غير أعجمي؟ أوضح بمثال",
      "هل يشترط أن يجتمع سبب من الأسباب مع التأنيث بالألف المقصورة والممدودة؟ أوضح مع الوجه",
      "أي الأسباب يجتمع مع العلمية مؤثرا وأي لا يجتمع؟",
      "كم شرطا للعجمة في منع الصرف؟ مثل لذلك",
      "هل يمنع من الصرف الاسم العجمي إذا كان ثلاثيا ساكن الأوسط؟ اذكر أمثلة لذلك",
      "كم شرطا للجمع في منع الصرف؟ وما هي؟ مثل له",
      "كيف يقوم سبب الجمع مقام السببين؟ أوضح بمثال",
      "كم شرطا للتركيب في منع الصرف؟ وما هي؟ مثل لذلك",
      "إذا كان التركيب بالإضافة أو الإسناد فهل يمنع من الصرف؟ وضح ذلك بمثال",
      "ما هو شرط الألف والنون الزائدتان لمنع الصرف في الاسم؟ وما شرطهما للمنع في الصفة؟ مثل لذلك",
      "اذكر شروط وزن الفعل في منع الصرف",
      "كم قسما لأسباب منع الصرف باعتبار العلمية؟ وما هي؟ بين مع الأحكام",
      "عدد أسباب منع الصرف التي تجتمع معها العلمية شرطا وعدد التي معها سببا",
      "كم صورة لتنكير الأعلام؟ وما هي؟ أوضح بأمثلة"
    ]
  },
  {
    "chapter": "المرفوعات - أسثلة الفاعل",
    "questions": [
      "كم قسما للأسماء المرفوعة وما هي؟ عددها مرتبة",
      "عرف الفاعل وبين فوائد قيود تعريفه",
      "كم شرطا لكون الاسم فاعلا وما هي؟",
      "كم قسما للفاعل؟ وما هي؟ أوضح بالأمثلة",
      "متى يجب توحيد الفعل؟ ومتى يجب مطابقة الفعل الفاعل؟ بين بالأمثلة",
      "اذكر مواضع تذكير الفعل وتأنيثه بالأمثلة",
      "ماذا حكم الفعل إذا كان الفاعل جمع المذكر السالم ظاهرا أو ضميرا؟ بين بالتمثيل"
    ]
  },
  {
    "chapter": "أسثلة التنازع",
    "questions": [
      "ما هو التنازع لغة واصطلاحا؟",
      "كم قسما للتنازع؟ اكتب كل قسم ممثلا",
      "ما الخلاف بين جمهور النحاة والإمام الفراء في الصورة الأولى والثالثة؟ أوضح دليل الفراء مع المثال",
      "ما هو مدار الخلاف بين العلماء البصريين والعلماء الكوفيين؟ وماذا قالوا؟ بين مدللا",
      "ماذا تفعل إن أعملت الثاني على مذهب البصريين ويقتضي الأول الفاعل؟ اكتب مع الأمثلة",
      "ماذا تفعل على مذهبهم إن كان الفعل الثاني يقيضي المفعول وكان الفعلان من أفعال القلوب؟ ولماذا؟ أوضح بالأمثلة",
      "ماذا تفعل إن أعملت الأول على مذهب الكوفيين والثاني يقتضي الفاعل؟ اكتب ممثلا",
      "وكم صورة تجوز علىى مذهبهم إن كان الفعل الثاني يقتضي المفعول ولم يكن الفعلان من أفعال القلوب؟ وما هو المختار؟ ولماذا؟ مثل كل صورة",
      "ماذا تفعل على مذهبهم إن كان الفعل الثاني يقتضي المفعول والفعلان من أفعال القلوب؟ بين بالأمثلة معللا"
    ]
  },
  {
    "chapter": "",
    "questions": ["", "", "", "", "", "", "", ""]
  },
  {
    "chapter": "",
    "questions": ["", "", "", "", "", "", "", ""]
  }
]
